pynometry/__init__.py
pynometry/p/1.txt
pynometry/p/10.txt
pynometry/p/2.txt
pynometry/p/3.txt
pynometry/p/4.txt
pynometry/p/5.txt
pynometry/p/6.txt
pynometry/p/7.txt
pynometry/p/8.txt
pynometry/p/9.txt
pynometry-0.1.0.dist-info/METADATA
pynometry-0.1.0.dist-info/WHEEL
pynometry-0.1.0.dist-info/top_level.txt
pynometry-0.1.0.dist-info/RECORD
