Metadata-Version: 2.4
Name: pynometry
Version: 0.1.0
Summary: A collection of Math functions
Author: Unknown
Classifier: Programming Language :: Python :: 3
Classifier: Operating System :: OS Independent
Requires-Python: >=3.6
Dynamic: author
Dynamic: classifier
Dynamic: requires-python
Dynamic: summary
